pypwr/ES_h.py
pypwr/ES_w1.py
pypwr/ES_w2.py
pypwr/__init__.py
pypwr/cohen_ES.py
pypwr/plot_power_htest.py
pypwr/pwr_2p2n_test.py
pypwr/pwr_2p_test.py
pypwr/pwr_anova_test.py
pypwr/pwr_chisq_test.py
pypwr/pwr_f2_test.py
pypwr/pwr_norm_test.py
pypwr/pwr_p_test.py
pypwr/pwr_r_test.py
pypwr/pwr_t2n_test.py
pypwr/pwr_t_test.py
pypwr-0.0.2.dist-info/LICENSE
pypwr-0.0.2.dist-info/METADATA
pypwr-0.0.2.dist-info/WHEEL
pypwr-0.0.2.dist-info/top_level.txt
pypwr-0.0.2.dist-info/RECORD
