Metadata-Version: 2.1
Name: pypwr
Version: 0.0.2
Summary: Python version of the pwr R package
Home-page: UNKNOWN
Author: Ernest (Khashayar) Namdar
Author-email: ernest.namdar@utoronto.ca
License: UNKNOWN
Platform: UNKNOWN
Classifier: Programming Language :: Python :: 3
Classifier: License :: OSI Approved :: MIT License
Classifier: Operating System :: OS Independent
License-File: LICENSE
